[
  {
    "run_id": "job-search-20260520-104137",
    "timestamp": "2026-05-20T10:41:37Z",
    "mode": "full",
    "platforms": "linkedin,glassdoor,indeed,reed",
    "status": {
      "initialize": "success",
      "discovery": "success",
      "keyword_extraction": "skipped",
      "matching": "success"
    }
  },
  {
    "run_id": "job-search-20260520-214224",
    "timestamp": "2026-05-20T21:42:24Z",
    "mode": "full",
    "platforms": "linkedin,glassdoor,indeed,reed",
    "status": {
      "initialize": "success",
      "discovery": "success",
      "keyword_extraction": "skipped",
      "matching": "success"
    }
  },
  {
    "run_id": "job-search-20260521-105816",
    "timestamp": "2026-05-21T10:58:16Z",
    "mode": "full",
    "platforms": "linkedin,glassdoor,indeed,reed",
    "status": {
      "initialize": "success",
      "discovery": "success",
      "keyword_extraction": "skipped",
      "matching": "success"
    }
  },
  {
    "run_id": "job-search-20260521-212116",
    "timestamp": "2026-05-21T21:21:16Z",
    "mode": "full",
    "platforms": "linkedin,glassdoor,indeed,reed",
    "status": {
      "initialize": "success",
      "discovery": "success",
      "keyword_extraction": "skipped",
      "matching": "success"
    }
  },
  {
    "run_id": "job-search-20260522-104126",
    "timestamp": "2026-05-22T10:41:26Z",
    "mode": "full",
    "platforms": "linkedin,glassdoor,indeed,reed",
    "status": {
      "initialize": "success",
      "discovery": "success",
      "keyword_extraction": "skipped",
      "matching": "success"
    }
  },
  {
    "run_id": "job-search-20260522-210311",
    "timestamp": "2026-05-22T21:03:11Z",
    "mode": "full",
    "platforms": "linkedin,glassdoor,indeed,reed",
    "status": {
      "initialize": "success",
      "discovery": "success",
      "keyword_extraction": "skipped",
      "matching": "success"
    }
  },
  {
    "run_id": "job-search-20260523-094257",
    "timestamp": "2026-05-23T09:42:57Z",
    "mode": "full",
    "platforms": "linkedin,glassdoor,indeed,reed",
    "status": {
      "initialize": "success",
      "discovery": "success",
      "keyword_extraction": "skipped",
      "matching": "success"
    }
  },
  {
    "run_id": "job-search-20260523-203840",
    "timestamp": "2026-05-23T20:38:40Z",
    "mode": "full",
    "platforms": "linkedin,glassdoor,indeed,reed",
    "status": {
      "initialize": "success",
      "discovery": "success",
      "keyword_extraction": "skipped",
      "matching": "success"
    }
  },
  {
    "run_id": "job-search-20260524-094738",
    "timestamp": "2026-05-24T09:47:38Z",
    "mode": "full",
    "platforms": "linkedin,glassdoor,indeed,reed",
    "status": {
      "initialize": "success",
      "discovery": "success",
      "keyword_extraction": "skipped",
      "matching": "success"
    }
  },
  {
    "run_id": "job-search-20260524-204226",
    "timestamp": "2026-05-24T20:42:26Z",
    "mode": "full",
    "platforms": "linkedin,glassdoor,indeed,reed",
    "status": {
      "initialize": "success",
      "discovery": "success",
      "keyword_extraction": "skipped",
      "matching": "success"
    }
  },
  {
    "run_id": "job-search-20260525-114302",
    "timestamp": "2026-05-25T11:43:02Z",
    "mode": "full",
    "platforms": "linkedin,glassdoor,indeed,reed",
    "status": {
      "initialize": "success",
      "discovery": "success",
      "keyword_extraction": "skipped",
      "matching": "success"
    }
  },
  {
    "run_id": "job-search-20260525-205715",
    "timestamp": "2026-05-25T20:57:15Z",
    "mode": "full",
    "platforms": "linkedin,glassdoor,indeed,reed",
    "status": {
      "initialize": "success",
      "discovery": "success",
      "keyword_extraction": "skipped",
      "matching": "success"
    }
  },
  {
    "run_id": "job-search-20260526-212816",
    "timestamp": "2026-05-26T21:28:16Z",
    "mode": "full",
    "platforms": "linkedin,glassdoor,indeed,reed",
    "status": {
      "initialize": "success",
      "discovery": "success",
      "keyword_extraction": "skipped",
      "matching": "success"
    }
  },
  {
    "run_id": "job-search-20260527-112917",
    "timestamp": "2026-05-27T11:29:17Z",
    "mode": "full",
    "platforms": "linkedin,glassdoor,indeed,reed",
    "status": {
      "initialize": "success",
      "discovery": "success",
      "keyword_extraction": "skipped",
      "matching": "success"
    }
  },
  {
    "run_id": "job-search-20260527-214607",
    "timestamp": "2026-05-27T21:46:07Z",
    "mode": "full",
    "platforms": "linkedin,glassdoor,indeed,reed",
    "status": {
      "initialize": "success",
      "discovery": "success",
      "keyword_extraction": "skipped",
      "matching": "success"
    }
  },
  {
    "run_id": "job-search-20260528-112857",
    "timestamp": "2026-05-28T11:28:57Z",
    "mode": "full",
    "platforms": "linkedin,glassdoor,indeed,reed",
    "status": {
      "initialize": "success",
      "discovery": "success",
      "keyword_extraction": "skipped",
      "matching": "success"
    }
  },
  {
    "run_id": "job-search-20260528-214920",
    "timestamp": "2026-05-28T21:49:20Z",
    "mode": "full",
    "platforms": "linkedin,glassdoor,indeed,reed",
    "status": {
      "initialize": "success",
      "discovery": "success",
      "keyword_extraction": "skipped",
      "matching": "success"
    }
  },
  {
    "run_id": "job-search-20260529-111910",
    "timestamp": "2026-05-29T11:19:10Z",
    "mode": "full",
    "platforms": "linkedin,glassdoor,indeed,reed",
    "status": {
      "initialize": "success",
      "discovery": "success",
      "keyword_extraction": "skipped",
      "matching": "success"
    }
  },
  {
    "run_id": "job-search-20260529-214433",
    "timestamp": "2026-05-29T21:44:33Z",
    "mode": "full",
    "platforms": "linkedin,glassdoor,indeed,reed",
    "status": {
      "initialize": "success",
      "discovery": "success",
      "keyword_extraction": "skipped",
      "matching": "success"
    }
  },
  {
    "run_id": "job-search-20260530-095058",
    "timestamp": "2026-05-30T09:50:58Z",
    "mode": "full",
    "platforms": "linkedin,glassdoor,indeed,reed",
    "status": {
      "initialize": "success",
      "discovery": "success",
      "keyword_extraction": "skipped",
      "matching": "success"
    }
  },
  {
    "run_id": "job-search-20260530-204401",
    "timestamp": "2026-05-30T20:44:01Z",
    "mode": "full",
    "platforms": "linkedin,glassdoor,indeed,reed",
    "status": {
      "initialize": "success",
      "discovery": "success",
      "keyword_extraction": "skipped",
      "matching": "success"
    }
  },
  {
    "run_id": "job-search-20260531-100658",
    "timestamp": "2026-05-31T10:06:58Z",
    "mode": "full",
    "platforms": "linkedin,glassdoor,indeed,reed",
    "status": {
      "initialize": "success",
      "discovery": "success",
      "keyword_extraction": "skipped",
      "matching": "success"
    }
  },
  {
    "run_id": "job-search-20260531-204855",
    "timestamp": "2026-05-31T20:48:55Z",
    "mode": "full",
    "platforms": "linkedin,glassdoor,indeed,reed",
    "status": {
      "initialize": "success",
      "discovery": "success",
      "keyword_extraction": "skipped",
      "matching": "success"
    }
  },
  {
    "run_id": "job-search-20260601-132712",
    "timestamp": "2026-06-01T13:27:12Z",
    "mode": "full",
    "platforms": "linkedin,glassdoor,indeed,reed",
    "status": {
      "initialize": "success",
      "discovery": "success",
      "keyword_extraction": "skipped",
      "matching": "success"
    }
  },
  {
    "run_id": "job-search-20260601-222945",
    "timestamp": "2026-06-01T22:29:45Z",
    "mode": "full",
    "platforms": "linkedin,glassdoor,indeed,reed",
    "status": {
      "initialize": "success",
      "discovery": "success",
      "keyword_extraction": "skipped",
      "matching": "success"
    }
  },
  {
    "run_id": "job-search-20260602-115713",
    "timestamp": "2026-06-02T11:57:13Z",
    "mode": "full",
    "platforms": "linkedin,glassdoor,indeed,reed",
    "status": {
      "initialize": "success",
      "discovery": "success",
      "keyword_extraction": "skipped",
      "matching": "success"
    }
  },
  {
    "run_id": "job-search-20260602-221654",
    "timestamp": "2026-06-02T22:16:54Z",
    "mode": "full",
    "platforms": "linkedin,glassdoor,indeed,reed",
    "status": {
      "initialize": "success",
      "discovery": "success",
      "keyword_extraction": "skipped",
      "matching": "success"
    }
  },
  {
    "run_id": "job-search-20260603-122949",
    "timestamp": "2026-06-03T12:29:49Z",
    "mode": "full",
    "platforms": "linkedin,glassdoor,indeed,reed",
    "status": {
      "initialize": "success",
      "discovery": "success",
      "keyword_extraction": "skipped",
      "matching": "success"
    }
  },
  {
    "run_id": "job-search-20260603-222321",
    "timestamp": "2026-06-03T22:23:21Z",
    "mode": "full",
    "platforms": "linkedin,glassdoor,indeed,reed",
    "status": {
      "initialize": "success",
      "discovery": "success",
      "keyword_extraction": "skipped",
      "matching": "success"
    }
  },
  {
    "run_id": "job-search-20260604-105431",
    "timestamp": "2026-06-04T10:54:31Z",
    "mode": "full",
    "platforms": "linkedin,glassdoor,indeed,reed",
    "status": {
      "initialize": "success",
      "discovery": "success",
      "keyword_extraction": "skipped",
      "matching": "success"
    }
  },
  {
    "run_id": "job-search-20260604-212320",
    "timestamp": "2026-06-04T21:23:20Z",
    "mode": "full",
    "platforms": "linkedin,glassdoor,indeed,reed",
    "status": {
      "initialize": "success",
      "discovery": "success",
      "keyword_extraction": "skipped",
      "matching": "success"
    }
  },
  {
    "run_id": "job-search-20260605-111750",
    "timestamp": "2026-06-05T11:17:50Z",
    "mode": "full",
    "platforms": "linkedin,glassdoor,indeed,reed",
    "status": {
      "initialize": "success",
      "discovery": "success",
      "keyword_extraction": "skipped",
      "matching": "success"
    }
  },
  {
    "run_id": "job-search-20260605-211657",
    "timestamp": "2026-06-05T21:16:57Z",
    "mode": "full",
    "platforms": "linkedin,glassdoor,indeed,reed",
    "status": {
      "initialize": "success",
      "discovery": "success",
      "keyword_extraction": "skipped",
      "matching": "success"
    }
  },
  {
    "run_id": "job-search-20260606-095405",
    "timestamp": "2026-06-06T09:54:05Z",
    "mode": "full",
    "platforms": "linkedin,glassdoor,indeed,reed",
    "status": {
      "initialize": "success",
      "discovery": "success",
      "keyword_extraction": "skipped",
      "matching": "success"
    }
  },
  {
    "run_id": "job-search-20260606-205414",
    "timestamp": "2026-06-06T20:54:14Z",
    "mode": "full",
    "platforms": "linkedin,glassdoor,indeed,reed",
    "status": {
      "initialize": "success",
      "discovery": "success",
      "keyword_extraction": "skipped",
      "matching": "success"
    }
  },
  {
    "run_id": "job-search-20260607-102142",
    "timestamp": "2026-06-07T10:21:42Z",
    "mode": "full",
    "platforms": "linkedin,glassdoor,indeed,reed",
    "status": {
      "initialize": "success",
      "discovery": "success",
      "keyword_extraction": "skipped",
      "matching": "success"
    }
  },
  {
    "run_id": "job-search-20260607-210025",
    "timestamp": "2026-06-07T21:00:25Z",
    "mode": "full",
    "platforms": "linkedin,glassdoor,indeed,reed",
    "status": {
      "initialize": "success",
      "discovery": "success",
      "keyword_extraction": "skipped",
      "matching": "success"
    }
  },
  {
    "run_id": "job-search-20260608-122132",
    "timestamp": "2026-06-08T12:21:32Z",
    "mode": "full",
    "platforms": "linkedin,glassdoor,indeed,reed",
    "status": {
      "initialize": "success",
      "discovery": "success",
      "keyword_extraction": "skipped",
      "matching": "success"
    }
  },
  {
    "run_id": "job-search-20260608-214421",
    "timestamp": "2026-06-08T21:44:21Z",
    "mode": "full",
    "platforms": "linkedin,glassdoor,indeed,reed",
    "status": {
      "initialize": "success",
      "discovery": "success",
      "keyword_extraction": "skipped",
      "matching": "success"
    }
  },
  {
    "run_id": "job-search-20260609-105121",
    "timestamp": "2026-06-09T10:51:21Z",
    "mode": "full",
    "platforms": "linkedin,glassdoor,indeed,reed",
    "status": {
      "initialize": "success",
      "discovery": "success",
      "keyword_extraction": "skipped",
      "matching": "success"
    }
  },
  {
    "run_id": "job-search-20260609-213023",
    "timestamp": "2026-06-09T21:30:23Z",
    "mode": "full",
    "platforms": "linkedin,glassdoor,indeed,reed",
    "status": {
      "initialize": "success",
      "discovery": "success",
      "keyword_extraction": "skipped",
      "matching": "success"
    }
  },
  {
    "run_id": "job-search-20260610-113015",
    "timestamp": "2026-06-10T11:30:15Z",
    "mode": "full",
    "platforms": "linkedin,glassdoor,indeed,reed",
    "status": {
      "initialize": "success",
      "discovery": "success",
      "keyword_extraction": "skipped",
      "matching": "success"
    }
  },
  {
    "run_id": "job-search-20260610-215031",
    "timestamp": "2026-06-10T21:50:31Z",
    "mode": "full",
    "platforms": "linkedin,glassdoor,indeed,reed",
    "status": {
      "initialize": "success",
      "discovery": "success",
      "keyword_extraction": "skipped",
      "matching": "success"
    }
  },
  {
    "run_id": "job-search-20260611-120227",
    "timestamp": "2026-06-11T12:02:27Z",
    "mode": "full",
    "platforms": "linkedin,glassdoor,indeed,reed",
    "status": {
      "initialize": "success",
      "discovery": "success",
      "keyword_extraction": "skipped",
      "matching": "success"
    }
  },
  {
    "run_id": "job-search-20260611-215332",
    "timestamp": "2026-06-11T21:53:32Z",
    "mode": "full",
    "platforms": "linkedin,glassdoor,indeed,reed",
    "status": {
      "initialize": "success",
      "discovery": "success",
      "keyword_extraction": "skipped",
      "matching": "success"
    }
  },
  {
    "run_id": "job-search-20260612-113513",
    "timestamp": "2026-06-12T11:35:13Z",
    "mode": "full",
    "platforms": "linkedin,glassdoor,indeed,reed",
    "status": {
      "initialize": "success",
      "discovery": "success",
      "keyword_extraction": "skipped",
      "matching": "success"
    }
  },
  {
    "run_id": "job-search-20260612-212351",
    "timestamp": "2026-06-12T21:23:51Z",
    "mode": "full",
    "platforms": "linkedin,glassdoor,indeed,reed",
    "status": {
      "initialize": "success",
      "discovery": "success",
      "keyword_extraction": "skipped",
      "matching": "success"
    }
  },
  {
    "run_id": "job-search-20260613-102109",
    "timestamp": "2026-06-13T10:21:09Z",
    "mode": "full",
    "platforms": "linkedin,glassdoor,indeed,reed",
    "status": {
      "initialize": "success",
      "discovery": "success",
      "keyword_extraction": "skipped",
      "matching": "success"
    }
  },
  {
    "run_id": "job-search-20260613-210222",
    "timestamp": "2026-06-13T21:02:22Z",
    "mode": "full",
    "platforms": "linkedin,glassdoor,indeed,reed",
    "status": {
      "initialize": "success",
      "discovery": "success",
      "keyword_extraction": "skipped",
      "matching": "success"
    }
  },
  {
    "run_id": "job-search-20260614-104352",
    "timestamp": "2026-06-14T10:43:52Z",
    "mode": "full",
    "platforms": "linkedin,glassdoor,indeed,reed",
    "status": {
      "initialize": "success",
      "discovery": "success",
      "keyword_extraction": "skipped",
      "matching": "success"
    }
  },
  {
    "run_id": "job-search-20260614-205937",
    "timestamp": "2026-06-14T20:59:37Z",
    "mode": "full",
    "platforms": "linkedin,glassdoor,indeed,reed",
    "status": {
      "initialize": "success",
      "discovery": "success",
      "keyword_extraction": "skipped",
      "matching": "success"
    }
  },
  {
    "run_id": "job-search-20260615-134549",
    "timestamp": "2026-06-15T13:45:49Z",
    "mode": "full",
    "platforms": "linkedin,glassdoor,indeed,reed",
    "status": {
      "initialize": "success",
      "discovery": "success",
      "keyword_extraction": "skipped",
      "matching": "success"
    }
  },
  {
    "run_id": "job-search-20260615-221007",
    "timestamp": "2026-06-15T22:10:07Z",
    "mode": "full",
    "platforms": "linkedin,glassdoor,indeed,reed",
    "status": {
      "initialize": "success",
      "discovery": "success",
      "keyword_extraction": "skipped",
      "matching": "success"
    }
  },
  {
    "run_id": "job-search-20260616-124511",
    "timestamp": "2026-06-16T12:45:11Z",
    "mode": "full",
    "platforms": "linkedin,glassdoor,indeed,reed",
    "status": {
      "initialize": "success",
      "discovery": "success",
      "keyword_extraction": "skipped",
      "matching": "success"
    }
  },
  {
    "run_id": "job-search-20260616-220502",
    "timestamp": "2026-06-16T22:05:02Z",
    "mode": "full",
    "platforms": "linkedin,glassdoor,indeed,reed",
    "status": {
      "initialize": "success",
      "discovery": "success",
      "keyword_extraction": "skipped",
      "matching": "success"
    }
  },
  {
    "run_id": "job-search-20260617-120941",
    "timestamp": "2026-06-17T12:09:41Z",
    "mode": "full",
    "platforms": "linkedin,glassdoor,indeed,reed",
    "status": {
      "initialize": "success",
      "discovery": "success",
      "keyword_extraction": "skipped",
      "matching": "success"
    }
  },
  {
    "run_id": "job-search-20260617-215252",
    "timestamp": "2026-06-17T21:52:52Z",
    "mode": "full",
    "platforms": "linkedin,glassdoor,indeed,reed",
    "status": {
      "initialize": "success",
      "discovery": "success",
      "keyword_extraction": "skipped",
      "matching": "success"
    }
  },
  {
    "run_id": "job-search-20260618-114448",
    "timestamp": "2026-06-18T11:44:48Z",
    "mode": "full",
    "platforms": "linkedin,glassdoor,indeed,reed",
    "status": {
      "initialize": "success",
      "discovery": "success",
      "keyword_extraction": "skipped",
      "matching": "success"
    }
  },
  {
    "run_id": "job-search-20260618-215658",
    "timestamp": "2026-06-18T21:56:58Z",
    "mode": "full",
    "platforms": "linkedin,glassdoor,indeed,reed",
    "status": {
      "initialize": "success",
      "discovery": "success",
      "keyword_extraction": "skipped",
      "matching": "success"
    }
  },
  {
    "run_id": "job-search-20260619-115819",
    "timestamp": "2026-06-19T11:58:19Z",
    "mode": "full",
    "platforms": "linkedin,glassdoor,indeed,reed",
    "status": {
      "initialize": "success",
      "discovery": "success",
      "keyword_extraction": "skipped",
      "matching": "success"
    }
  },
  {
    "run_id": "job-search-20260619-210110",
    "timestamp": "2026-06-19T21:01:10Z",
    "mode": "full",
    "platforms": "linkedin,glassdoor,indeed,reed",
    "status": {
      "initialize": "success",
      "discovery": "success",
      "keyword_extraction": "skipped",
      "matching": "success"
    }
  },
  {
    "run_id": "job-search-20260620-102621",
    "timestamp": "2026-06-20T10:26:21Z",
    "mode": "full",
    "platforms": "linkedin,glassdoor,indeed,reed",
    "status": {
      "initialize": "success",
      "discovery": "success",
      "keyword_extraction": "skipped",
      "matching": "success"
    }
  },
  {
    "run_id": "job-search-20260620-210358",
    "timestamp": "2026-06-20T21:03:58Z",
    "mode": "full",
    "platforms": "linkedin,glassdoor,indeed,reed",
    "status": {
      "initialize": "success",
      "discovery": "success",
      "keyword_extraction": "skipped",
      "matching": "success"
    }
  },
  {
    "run_id": "job-search-20260621-105934",
    "timestamp": "2026-06-21T10:59:34Z",
    "mode": "full",
    "platforms": "linkedin,glassdoor,indeed,reed",
    "status": {
      "initialize": "success",
      "discovery": "success",
      "keyword_extraction": "skipped",
      "matching": "success"
    }
  },
  {
    "run_id": "job-search-20260621-210441",
    "timestamp": "2026-06-21T21:04:41Z",
    "mode": "full",
    "platforms": "linkedin,glassdoor,indeed,reed",
    "status": {
      "initialize": "success",
      "discovery": "success",
      "keyword_extraction": "skipped",
      "matching": "success"
    }
  },
  {
    "run_id": "job-search-20260622-132613",
    "timestamp": "2026-06-22T13:26:13Z",
    "mode": "full",
    "platforms": "linkedin,glassdoor,indeed,reed",
    "status": {
      "initialize": "success",
      "discovery": "success",
      "keyword_extraction": "skipped",
      "matching": "success"
    }
  },
  {
    "run_id": "job-search-20260622-215516",
    "timestamp": "2026-06-22T21:55:16Z",
    "mode": "full",
    "platforms": "linkedin,glassdoor,indeed,reed",
    "status": {
      "initialize": "success",
      "discovery": "success",
      "keyword_extraction": "skipped",
      "matching": "success"
    }
  },
  {
    "run_id": "job-search-20260623-105425",
    "timestamp": "2026-06-23T10:54:25Z",
    "mode": "full",
    "platforms": "linkedin,glassdoor,indeed,reed",
    "status": {
      "initialize": "success",
      "discovery": "success",
      "keyword_extraction": "skipped",
      "matching": "success"
    }
  },
  {
    "run_id": "job-search-20260623-212353",
    "timestamp": "2026-06-23T21:23:53Z",
    "mode": "full",
    "platforms": "linkedin,glassdoor,indeed,reed",
    "status": {
      "initialize": "success",
      "discovery": "success",
      "keyword_extraction": "skipped",
      "matching": "success"
    }
  },
  {
    "run_id": "job-search-20260624-104019",
    "timestamp": "2026-06-24T10:40:19Z",
    "mode": "full",
    "platforms": "linkedin,glassdoor,indeed,reed",
    "status": {
      "initialize": "success",
      "discovery": "success",
      "keyword_extraction": "skipped",
      "matching": "success"
    }
  },
  {
    "run_id": "job-search-20260624-211618",
    "timestamp": "2026-06-24T21:16:18Z",
    "mode": "full",
    "platforms": "linkedin,glassdoor,indeed,reed",
    "status": {
      "initialize": "success",
      "discovery": "success",
      "keyword_extraction": "skipped",
      "matching": "success"
    }
  },
  {
    "run_id": "job-search-20260625-103349",
    "timestamp": "2026-06-25T10:33:49Z",
    "mode": "full",
    "platforms": "linkedin,glassdoor,indeed,reed",
    "status": {
      "initialize": "success",
      "discovery": "success",
      "keyword_extraction": "skipped",
      "matching": "success"
    }
  },
  {
    "run_id": "job-search-20260625-212143",
    "timestamp": "2026-06-25T21:21:43Z",
    "mode": "full",
    "platforms": "linkedin,glassdoor,indeed,reed",
    "status": {
      "initialize": "success",
      "discovery": "success",
      "keyword_extraction": "skipped",
      "matching": "success"
    }
  },
  {
    "run_id": "job-search-20260626-104323",
    "timestamp": "2026-06-26T10:43:23Z",
    "mode": "full",
    "platforms": "linkedin,glassdoor,indeed,reed",
    "status": {
      "initialize": "success",
      "discovery": "success",
      "keyword_extraction": "skipped",
      "matching": "success"
    }
  },
  {
    "run_id": "job-search-20260626-211154",
    "timestamp": "2026-06-26T21:11:54Z",
    "mode": "full",
    "platforms": "linkedin,glassdoor,indeed,reed",
    "status": {
      "initialize": "success",
      "discovery": "success",
      "keyword_extraction": "skipped",
      "matching": "success"
    }
  },
  {
    "run_id": "job-search-20260627-095608",
    "timestamp": "2026-06-27T09:56:08Z",
    "mode": "full",
    "platforms": "linkedin,glassdoor,indeed,reed",
    "status": {
      "initialize": "success",
      "discovery": "success",
      "keyword_extraction": "skipped",
      "matching": "success"
    }
  },
  {
    "run_id": "job-search-20260627-205045",
    "timestamp": "2026-06-27T20:50:45Z",
    "mode": "full",
    "platforms": "linkedin,glassdoor,indeed,reed",
    "status": {
      "initialize": "success",
      "discovery": "success",
      "keyword_extraction": "skipped",
      "matching": "success"
    }
  },
  {
    "run_id": "job-search-20260628-102019",
    "timestamp": "2026-06-28T10:20:19Z",
    "mode": "full",
    "platforms": "linkedin,glassdoor,indeed,reed",
    "status": {
      "initialize": "success",
      "discovery": "success",
      "keyword_extraction": "skipped",
      "matching": "success"
    }
  },
  {
    "run_id": "job-search-20260628-205148",
    "timestamp": "2026-06-28T20:51:48Z",
    "mode": "full",
    "platforms": "linkedin,glassdoor,indeed,reed",
    "status": {
      "initialize": "success",
      "discovery": "success",
      "keyword_extraction": "skipped",
      "matching": "success"
    }
  },
  {
    "run_id": "job-search-20260629-122228",
    "timestamp": "2026-06-29T12:22:28Z",
    "mode": "full",
    "platforms": "linkedin,glassdoor,indeed,reed",
    "status": {
      "initialize": "success",
      "discovery": "success",
      "keyword_extraction": "skipped",
      "matching": "success"
    }
  },
  {
    "run_id": "job-search-20260629-211648",
    "timestamp": "2026-06-29T21:16:48Z",
    "mode": "full",
    "platforms": "linkedin,glassdoor,indeed,reed",
    "status": {
      "initialize": "success",
      "discovery": "success",
      "keyword_extraction": "skipped",
      "matching": "success"
    }
  },
  {
    "run_id": "job-search-20260630-104815",
    "timestamp": "2026-06-30T10:48:15Z",
    "mode": "full",
    "platforms": "linkedin,glassdoor,indeed,reed",
    "status": {
      "initialize": "success",
      "discovery": "success",
      "keyword_extraction": "skipped",
      "matching": "success"
    }
  },
  {
    "run_id": "job-search-20260630-212152",
    "timestamp": "2026-06-30T21:21:52Z",
    "mode": "full",
    "platforms": "linkedin,glassdoor,indeed,reed",
    "status": {
      "initialize": "success",
      "discovery": "success",
      "keyword_extraction": "skipped",
      "matching": "success"
    }
  },
  {
    "run_id": "job-search-20260701-111645",
    "timestamp": "2026-07-01T11:16:45Z",
    "mode": "full",
    "platforms": "linkedin,glassdoor,indeed,reed",
    "status": {
      "initialize": "success",
      "discovery": "success",
      "keyword_extraction": "skipped",
      "matching": "success"
    }
  },
  {
    "run_id": "job-search-20260701-211743",
    "timestamp": "2026-07-01T21:17:43Z",
    "mode": "full",
    "platforms": "linkedin,glassdoor,indeed,reed",
    "status": {
      "initialize": "success",
      "discovery": "success",
      "keyword_extraction": "skipped",
      "matching": "success"
    }
  },
  {
    "run_id": "job-search-20260702-102814",
    "timestamp": "2026-07-02T10:28:14Z",
    "mode": "full",
    "platforms": "linkedin,glassdoor,indeed,reed",
    "status": {
      "initialize": "success",
      "discovery": "success",
      "keyword_extraction": "skipped",
      "matching": "success"
    }
  },
  {
    "run_id": "job-search-20260702-205351",
    "timestamp": "2026-07-02T20:53:51Z",
    "mode": "full",
    "platforms": "linkedin,glassdoor,indeed,reed",
    "status": {
      "initialize": "success",
      "discovery": "success",
      "keyword_extraction": "skipped",
      "matching": "success"
    }
  },
  {
    "run_id": "job-search-20260703-102607",
    "timestamp": "2026-07-03T10:26:07Z",
    "mode": "full",
    "platforms": "linkedin,glassdoor,indeed,reed",
    "status": {
      "initialize": "success",
      "discovery": "success",
      "keyword_extraction": "skipped",
      "matching": "success"
    }
  },
  {
    "run_id": "job-search-20260703-205238",
    "timestamp": "2026-07-03T20:52:38Z",
    "mode": "full",
    "platforms": "linkedin,glassdoor,indeed,reed",
    "status": {
      "initialize": "success",
      "discovery": "success",
      "keyword_extraction": "skipped",
      "matching": "success"
    }
  },
  {
    "run_id": "job-search-20260704-095922",
    "timestamp": "2026-07-04T09:59:22Z",
    "mode": "full",
    "platforms": "linkedin,glassdoor,indeed,reed",
    "status": {
      "initialize": "success",
      "discovery": "success",
      "keyword_extraction": "skipped",
      "matching": "success"
    }
  },
  {
    "run_id": "job-search-20260704-204302",
    "timestamp": "2026-07-04T20:43:02Z",
    "mode": "full",
    "platforms": "linkedin,glassdoor,indeed,reed",
    "status": {
      "initialize": "success",
      "discovery": "success",
      "keyword_extraction": "skipped",
      "matching": "success"
    }
  },
  {
    "run_id": "job-search-20260705-100319",
    "timestamp": "2026-07-05T10:03:19Z",
    "mode": "full",
    "platforms": "linkedin,glassdoor,indeed,reed",
    "status": {
      "initialize": "success",
      "discovery": "success",
      "keyword_extraction": "skipped",
      "matching": "success"
    }
  },
  {
    "run_id": "job-search-20260705-204638",
    "timestamp": "2026-07-05T20:46:38Z",
    "mode": "full",
    "platforms": "linkedin,glassdoor,indeed,reed",
    "status": {
      "initialize": "success",
      "discovery": "success",
      "keyword_extraction": "skipped",
      "matching": "success"
    }
  },
  {
    "run_id": "job-search-20260706-115503",
    "timestamp": "2026-07-06T11:55:03Z",
    "mode": "full",
    "platforms": "linkedin,glassdoor,indeed,reed",
    "status": {
      "initialize": "success",
      "discovery": "success",
      "keyword_extraction": "skipped",
      "matching": "success"
    }
  },
  {
    "run_id": "job-search-20260706-212057",
    "timestamp": "2026-07-06T21:20:57Z",
    "mode": "full",
    "platforms": "linkedin,glassdoor,indeed,reed",
    "status": {
      "initialize": "success",
      "discovery": "success",
      "keyword_extraction": "skipped",
      "matching": "success"
    }
  },
  {
    "run_id": "job-search-20260707-104521",
    "timestamp": "2026-07-07T10:45:21Z",
    "mode": "full",
    "platforms": "linkedin,glassdoor,indeed,reed",
    "status": {
      "initialize": "success",
      "discovery": "success",
      "keyword_extraction": "skipped",
      "matching": "success"
    }
  },
  {
    "run_id": "job-search-20260707-211500",
    "timestamp": "2026-07-07T21:15:00Z",
    "mode": "full",
    "platforms": "linkedin,glassdoor,indeed,reed",
    "status": {
      "initialize": "success",
      "discovery": "success",
      "keyword_extraction": "skipped",
      "matching": "success"
    }
  },
  {
    "run_id": "job-search-20260708-100709",
    "timestamp": "2026-07-08T10:07:09Z",
    "mode": "full",
    "platforms": "linkedin,glassdoor,indeed,reed",
    "status": {
      "initialize": "success",
      "discovery": "success",
      "keyword_extraction": "skipped",
      "matching": "success"
    }
  },
  {
    "run_id": "job-search-20260708-205622",
    "timestamp": "2026-07-08T20:56:22Z",
    "mode": "full",
    "platforms": "linkedin,glassdoor,indeed,reed",
    "status": {
      "initialize": "success",
      "discovery": "success",
      "keyword_extraction": "skipped",
      "matching": "success"
    }
  },
  {
    "run_id": "job-search-20260709-104502",
    "timestamp": "2026-07-09T10:45:02Z",
    "mode": "full",
    "platforms": "linkedin,glassdoor,indeed,reed",
    "status": {
      "initialize": "success",
      "discovery": "success",
      "keyword_extraction": "skipped",
      "matching": "success"
    }
  }
]